{"__symbolic":"module","version":4,"metadata":{"Pcm":{"PCM_16":0,"PCM_24":1,"PCM_32":2,"PCM_S8":3,"PCM_U8":4,"FLOAT":5,"DOUBLE":6},"AudioFormat":{"wav":0,"flac":1,"caf":2,"mp3":3,"aac":4,"ogg":5,"wma":6},"SynthesizeRequest":{"__symbolic":"class","members":{"__ctor__":[{"__symbolic":"constructor","parameters":[{"__symbolic":"reference","name":"RecursivePartial","module":"@ngx-grpc/common","arguments":[{"__symbolic":"select","expression":{"__symbolic":"reference","name":"Apodization"},"member":"AsObject"}]}]}],"serializeBinary":[{"__symbolic":"method"}],"toObject":[{"__symbolic":"method"}],"toJSON":[{"__symbolic":"method"}],"toProtobufJSON":[{"__symbolic":"method"}]},"statics":{"id":"ondewo.t2s.SynthesizeRequest"}},"BatchSynthesizeRequest":{"__symbolic":"class","members":{"__ctor__":[{"__symbolic":"constructor","parameters":[{"__symbolic":"reference","name":"RecursivePartial","module":"@ngx-grpc/common","arguments":[{"__symbolic":"select","expression":{"__symbolic":"reference","name":"Apodization"},"member":"AsObject"}]}]}],"serializeBinary":[{"__symbolic":"method"}],"toObject":[{"__symbolic":"method"}],"toJSON":[{"__symbolic":"method"}],"toProtobufJSON":[{"__symbolic":"method"}]},"statics":{"id":"ondewo.t2s.BatchSynthesizeRequest"}},"BatchSynthesizeResponse":{"__symbolic":"class","members":{"__ctor__":[{"__symbolic":"constructor","parameters":[{"__symbolic":"reference","name":"RecursivePartial","module":"@ngx-grpc/common","arguments":[{"__symbolic":"select","expression":{"__symbolic":"reference","name":"Apodization"},"member":"AsObject"}]}]}],"serializeBinary":[{"__symbolic":"method"}],"toObject":[{"__symbolic":"method"}],"toJSON":[{"__symbolic":"method"}],"toProtobufJSON":[{"__symbolic":"method"}]},"statics":{"id":"ondewo.t2s.BatchSynthesizeResponse"}},"RequestConfig":{"__symbolic":"class","members":{"__ctor__":[{"__symbolic":"constructor","parameters":[{"__symbolic":"reference","name":"RecursivePartial","module":"@ngx-grpc/common","arguments":[{"__symbolic":"select","expression":{"__symbolic":"reference","name":"Apodization"},"member":"AsObject"}]}]}],"serializeBinary":[{"__symbolic":"method"}],"toObject":[{"__symbolic":"method"}],"toJSON":[{"__symbolic":"method"}],"toProtobufJSON":[{"__symbolic":"method"}]},"statics":{"id":"ondewo.t2s.RequestConfig"}},"SynthesizeResponse":{"__symbolic":"class","members":{"__ctor__":[{"__symbolic":"constructor","parameters":[{"__symbolic":"reference","name":"RecursivePartial","module":"@ngx-grpc/common","arguments":[{"__symbolic":"select","expression":{"__symbolic":"reference","name":"Apodization"},"member":"AsObject"}]}]}],"serializeBinary":[{"__symbolic":"method"}],"toObject":[{"__symbolic":"method"}],"toJSON":[{"__symbolic":"method"}],"toProtobufJSON":[{"__symbolic":"method"}]},"statics":{"id":"ondewo.t2s.SynthesizeResponse"}},"GetServiceInfoResponse":{"__symbolic":"class","members":{"__ctor__":[{"__symbolic":"constructor","parameters":[{"__symbolic":"reference","name":"RecursivePartial","module":"@ngx-grpc/common","arguments":[{"__symbolic":"select","expression":{"__symbolic":"reference","name":"Apodization"},"member":"AsObject"}]}]}],"serializeBinary":[{"__symbolic":"method"}],"toObject":[{"__symbolic":"method"}],"toJSON":[{"__symbolic":"method"}],"toProtobufJSON":[{"__symbolic":"method"}]},"statics":{"id":"ondewo.t2s.GetServiceInfoResponse"}},"ListT2sPipelinesRequest":{"__symbolic":"class","members":{"__ctor__":[{"__symbolic":"constructor","parameters":[{"__symbolic":"reference","name":"RecursivePartial","module":"@ngx-grpc/common","arguments":[{"__symbolic":"select","expression":{"__symbolic":"reference","name":"Apodization"},"member":"AsObject"}]}]}],"serializeBinary":[{"__symbolic":"method"}],"toObject":[{"__symbolic":"method"}],"toJSON":[{"__symbolic":"method"}],"toProtobufJSON":[{"__symbolic":"method"}]},"statics":{"id":"ondewo.t2s.ListT2sPipelinesRequest"}},"ListT2sPipelinesResponse":{"__symbolic":"class","members":{"__ctor__":[{"__symbolic":"constructor","parameters":[{"__symbolic":"reference","name":"RecursivePartial","module":"@ngx-grpc/common","arguments":[{"__symbolic":"select","expression":{"__symbolic":"reference","name":"Apodization"},"member":"AsObject"}]}]}],"serializeBinary":[{"__symbolic":"method"}],"toObject":[{"__symbolic":"method"}],"toJSON":[{"__symbolic":"method"}],"toProtobufJSON":[{"__symbolic":"method"}]},"statics":{"id":"ondewo.t2s.ListT2sPipelinesResponse"}},"ListT2sLanguagesRequest":{"__symbolic":"class","members":{"__ctor__":[{"__symbolic":"constructor","parameters":[{"__symbolic":"reference","name":"RecursivePartial","module":"@ngx-grpc/common","arguments":[{"__symbolic":"select","expression":{"__symbolic":"reference","name":"Apodization"},"member":"AsObject"}]}]}],"serializeBinary":[{"__symbolic":"method"}],"toObject":[{"__symbolic":"method"}],"toJSON":[{"__symbolic":"method"}],"toProtobufJSON":[{"__symbolic":"method"}]},"statics":{"id":"ondewo.t2s.ListT2sLanguagesRequest"}},"ListT2sLanguagesResponse":{"__symbolic":"class","members":{"__ctor__":[{"__symbolic":"constructor","parameters":[{"__symbolic":"reference","name":"RecursivePartial","module":"@ngx-grpc/common","arguments":[{"__symbolic":"select","expression":{"__symbolic":"reference","name":"Apodization"},"member":"AsObject"}]}]}],"serializeBinary":[{"__symbolic":"method"}],"toObject":[{"__symbolic":"method"}],"toJSON":[{"__symbolic":"method"}],"toProtobufJSON":[{"__symbolic":"method"}]},"statics":{"id":"ondewo.t2s.ListT2sLanguagesResponse"}},"ListT2sDomainsRequest":{"__symbolic":"class","members":{"__ctor__":[{"__symbolic":"constructor","parameters":[{"__symbolic":"reference","name":"RecursivePartial","module":"@ngx-grpc/common","arguments":[{"__symbolic":"select","expression":{"__symbolic":"reference","name":"Apodization"},"member":"AsObject"}]}]}],"serializeBinary":[{"__symbolic":"method"}],"toObject":[{"__symbolic":"method"}],"toJSON":[{"__symbolic":"method"}],"toProtobufJSON":[{"__symbolic":"method"}]},"statics":{"id":"ondewo.t2s.ListT2sDomainsRequest"}},"ListT2sDomainsResponse":{"__symbolic":"class","members":{"__ctor__":[{"__symbolic":"constructor","parameters":[{"__symbolic":"reference","name":"RecursivePartial","module":"@ngx-grpc/common","arguments":[{"__symbolic":"select","expression":{"__symbolic":"reference","name":"Apodization"},"member":"AsObject"}]}]}],"serializeBinary":[{"__symbolic":"method"}],"toObject":[{"__symbolic":"method"}],"toJSON":[{"__symbolic":"method"}],"toProtobufJSON":[{"__symbolic":"method"}]},"statics":{"id":"ondewo.t2s.ListT2sDomainsResponse"}},"T2sPipelineId":{"__symbolic":"class","members":{"__ctor__":[{"__symbolic":"constructor","parameters":[{"__symbolic":"reference","name":"RecursivePartial","module":"@ngx-grpc/common","arguments":[{"__symbolic":"select","expression":{"__symbolic":"reference","name":"Apodization"},"member":"AsObject"}]}]}],"serializeBinary":[{"__symbolic":"method"}],"toObject":[{"__symbolic":"method"}],"toJSON":[{"__symbolic":"method"}],"toProtobufJSON":[{"__symbolic":"method"}]},"statics":{"id":"ondewo.t2s.T2sPipelineId"}},"Text2SpeechConfig":{"__symbolic":"class","members":{"__ctor__":[{"__symbolic":"constructor","parameters":[{"__symbolic":"reference","name":"RecursivePartial","module":"@ngx-grpc/common","arguments":[{"__symbolic":"select","expression":{"__symbolic":"reference","name":"Apodization"},"member":"AsObject"}]}]}],"serializeBinary":[{"__symbolic":"method"}],"toObject":[{"__symbolic":"method"}],"toJSON":[{"__symbolic":"method"}],"toProtobufJSON":[{"__symbolic":"method"}]},"statics":{"id":"ondewo.t2s.Text2SpeechConfig"}},"Description":{"__symbolic":"class","members":{"__ctor__":[{"__symbolic":"constructor","parameters":[{"__symbolic":"reference","name":"RecursivePartial","module":"@ngx-grpc/common","arguments":[{"__symbolic":"select","expression":{"__symbolic":"reference","name":"Apodization"},"member":"AsObject"}]}]}],"serializeBinary":[{"__symbolic":"method"}],"toObject":[{"__symbolic":"method"}],"toJSON":[{"__symbolic":"method"}],"toProtobufJSON":[{"__symbolic":"method"}]},"statics":{"id":"ondewo.t2s.Description"}},"Inference":{"__symbolic":"class","members":{"__ctor__":[{"__symbolic":"constructor","parameters":[{"__symbolic":"reference","name":"RecursivePartial","module":"@ngx-grpc/common","arguments":[{"__symbolic":"select","expression":{"__symbolic":"reference","name":"Apodization"},"member":"AsObject"}]}]}],"serializeBinary":[{"__symbolic":"method"}],"toObject":[{"__symbolic":"method"}],"toJSON":[{"__symbolic":"method"}],"toProtobufJSON":[{"__symbolic":"method"}]},"statics":{"id":"ondewo.t2s.Inference"}},"CompositeInference":{"__symbolic":"class","members":{"__ctor__":[{"__symbolic":"constructor","parameters":[{"__symbolic":"reference","name":"RecursivePartial","module":"@ngx-grpc/common","arguments":[{"__symbolic":"select","expression":{"__symbolic":"reference","name":"Apodization"},"member":"AsObject"}]}]}],"serializeBinary":[{"__symbolic":"method"}],"toObject":[{"__symbolic":"method"}],"toJSON":[{"__symbolic":"method"}],"toProtobufJSON":[{"__symbolic":"method"}]},"statics":{"id":"ondewo.t2s.CompositeInference"}},"Text2Mel":{"__symbolic":"class","members":{"__ctor__":[{"__symbolic":"constructor","parameters":[{"__symbolic":"reference","name":"RecursivePartial","module":"@ngx-grpc/common","arguments":[{"__symbolic":"select","expression":{"__symbolic":"reference","name":"Apodization"},"member":"AsObject"}]}]}],"serializeBinary":[{"__symbolic":"method"}],"toObject":[{"__symbolic":"method"}],"toJSON":[{"__symbolic":"method"}],"toProtobufJSON":[{"__symbolic":"method"}]},"statics":{"id":"ondewo.t2s.Text2Mel"}},"GlowTTS":{"__symbolic":"class","members":{"__ctor__":[{"__symbolic":"constructor","parameters":[{"__symbolic":"reference","name":"RecursivePartial","module":"@ngx-grpc/common","arguments":[{"__symbolic":"select","expression":{"__symbolic":"reference","name":"Apodization"},"member":"AsObject"}]}]}],"serializeBinary":[{"__symbolic":"method"}],"toObject":[{"__symbolic":"method"}],"toJSON":[{"__symbolic":"method"}],"toProtobufJSON":[{"__symbolic":"method"}]},"statics":{"id":"ondewo.t2s.GlowTTS"}},"GlowTTSTriton":{"__symbolic":"class","members":{"__ctor__":[{"__symbolic":"constructor","parameters":[{"__symbolic":"reference","name":"RecursivePartial","module":"@ngx-grpc/common","arguments":[{"__symbolic":"select","expression":{"__symbolic":"reference","name":"Apodization"},"member":"AsObject"}]}]}],"serializeBinary":[{"__symbolic":"method"}],"toObject":[{"__symbolic":"method"}],"toJSON":[{"__symbolic":"method"}],"toProtobufJSON":[{"__symbolic":"method"}]},"statics":{"id":"ondewo.t2s.GlowTTSTriton"}},"Mel2Audio":{"__symbolic":"class","members":{"__ctor__":[{"__symbolic":"constructor","parameters":[{"__symbolic":"reference","name":"RecursivePartial","module":"@ngx-grpc/common","arguments":[{"__symbolic":"select","expression":{"__symbolic":"reference","name":"Apodization"},"member":"AsObject"}]}]}],"serializeBinary":[{"__symbolic":"method"}],"toObject":[{"__symbolic":"method"}],"toJSON":[{"__symbolic":"method"}],"toProtobufJSON":[{"__symbolic":"method"}]},"statics":{"id":"ondewo.t2s.Mel2Audio"}},"HiFiGan":{"__symbolic":"class","members":{"__ctor__":[{"__symbolic":"constructor","parameters":[{"__symbolic":"reference","name":"RecursivePartial","module":"@ngx-grpc/common","arguments":[{"__symbolic":"select","expression":{"__symbolic":"reference","name":"Apodization"},"member":"AsObject"}]}]}],"serializeBinary":[{"__symbolic":"method"}],"toObject":[{"__symbolic":"method"}],"toJSON":[{"__symbolic":"method"}],"toProtobufJSON":[{"__symbolic":"method"}]},"statics":{"id":"ondewo.t2s.HiFiGan"}},"HiFiGanTriton":{"__symbolic":"class","members":{"__ctor__":[{"__symbolic":"constructor","parameters":[{"__symbolic":"reference","name":"RecursivePartial","module":"@ngx-grpc/common","arguments":[{"__symbolic":"select","expression":{"__symbolic":"reference","name":"Apodization"},"member":"AsObject"}]}]}],"serializeBinary":[{"__symbolic":"method"}],"toObject":[{"__symbolic":"method"}],"toJSON":[{"__symbolic":"method"}],"toProtobufJSON":[{"__symbolic":"method"}]},"statics":{"id":"ondewo.t2s.HiFiGanTriton"}},"MbMelganTriton":{"__symbolic":"class","members":{"__ctor__":[{"__symbolic":"constructor","parameters":[{"__symbolic":"reference","name":"RecursivePartial","module":"@ngx-grpc/common","arguments":[{"__symbolic":"select","expression":{"__symbolic":"reference","name":"Apodization"},"member":"AsObject"}]}]}],"serializeBinary":[{"__symbolic":"method"}],"toObject":[{"__symbolic":"method"}],"toJSON":[{"__symbolic":"method"}],"toProtobufJSON":[{"__symbolic":"method"}]},"statics":{"id":"ondewo.t2s.MbMelganTriton"}},"Caching":{"__symbolic":"class","members":{"__ctor__":[{"__symbolic":"constructor","parameters":[{"__symbolic":"reference","name":"RecursivePartial","module":"@ngx-grpc/common","arguments":[{"__symbolic":"select","expression":{"__symbolic":"reference","name":"Apodization"},"member":"AsObject"}]}]}],"serializeBinary":[{"__symbolic":"method"}],"toObject":[{"__symbolic":"method"}],"toJSON":[{"__symbolic":"method"}],"toProtobufJSON":[{"__symbolic":"method"}]},"statics":{"id":"ondewo.t2s.Caching"}},"Normalization":{"__symbolic":"class","members":{"__ctor__":[{"__symbolic":"constructor","parameters":[{"__symbolic":"reference","name":"RecursivePartial","module":"@ngx-grpc/common","arguments":[{"__symbolic":"select","expression":{"__symbolic":"reference","name":"Apodization"},"member":"AsObject"}]}]}],"serializeBinary":[{"__symbolic":"method"}],"toObject":[{"__symbolic":"method"}],"toJSON":[{"__symbolic":"method"}],"toProtobufJSON":[{"__symbolic":"method"}]},"statics":{"id":"ondewo.t2s.Normalization"}},"Postprocessing":{"__symbolic":"class","members":{"__ctor__":[{"__symbolic":"constructor","parameters":[{"__symbolic":"reference","name":"RecursivePartial","module":"@ngx-grpc/common","arguments":[{"__symbolic":"select","expression":{"__symbolic":"reference","name":"Apodization"},"member":"AsObject"}]}]}],"serializeBinary":[{"__symbolic":"method"}],"toObject":[{"__symbolic":"method"}],"toJSON":[{"__symbolic":"method"}],"toProtobufJSON":[{"__symbolic":"method"}]},"statics":{"id":"ondewo.t2s.Postprocessing"}},"Logmnse":{"__symbolic":"class","members":{"__ctor__":[{"__symbolic":"constructor","parameters":[{"__symbolic":"reference","name":"RecursivePartial","module":"@ngx-grpc/common","arguments":[{"__symbolic":"select","expression":{"__symbolic":"reference","name":"Apodization"},"member":"AsObject"}]}]}],"serializeBinary":[{"__symbolic":"method"}],"toObject":[{"__symbolic":"method"}],"toJSON":[{"__symbolic":"method"}],"toProtobufJSON":[{"__symbolic":"method"}]},"statics":{"id":"ondewo.t2s.Logmnse"}},"Wiener":{"__symbolic":"class","members":{"__ctor__":[{"__symbolic":"constructor","parameters":[{"__symbolic":"reference","name":"RecursivePartial","module":"@ngx-grpc/common","arguments":[{"__symbolic":"select","expression":{"__symbolic":"reference","name":"Apodization"},"member":"AsObject"}]}]}],"serializeBinary":[{"__symbolic":"method"}],"toObject":[{"__symbolic":"method"}],"toJSON":[{"__symbolic":"method"}],"toProtobufJSON":[{"__symbolic":"method"}]},"statics":{"id":"ondewo.t2s.Wiener"}},"Apodization":{"__symbolic":"class","members":{"__ctor__":[{"__symbolic":"constructor","parameters":[{"__symbolic":"reference","name":"RecursivePartial","module":"@ngx-grpc/common","arguments":[{"__symbolic":"select","expression":{"__symbolic":"reference","name":"Apodization"},"member":"AsObject"}]}]}],"serializeBinary":[{"__symbolic":"method"}],"toObject":[{"__symbolic":"method"}],"toJSON":[{"__symbolic":"method"}],"toProtobufJSON":[{"__symbolic":"method"}]},"statics":{"id":"ondewo.t2s.Apodization"}},"PhonemizerId":{"__symbolic":"class","members":{"__ctor__":[{"__symbolic":"constructor","parameters":[{"__symbolic":"reference","name":"RecursivePartial","module":"@ngx-grpc/common","arguments":[{"__symbolic":"select","expression":{"__symbolic":"reference","name":"CreateCustomPhonemizerRequest"},"member":"AsObject"}]}]}],"serializeBinary":[{"__symbolic":"method"}],"toObject":[{"__symbolic":"method"}],"toJSON":[{"__symbolic":"method"}],"toProtobufJSON":[{"__symbolic":"method"}]},"statics":{"id":"ondewo.t2s.PhonemizerId"}},"CustomPhonemizerProto":{"__symbolic":"class","members":{"__ctor__":[{"__symbolic":"constructor","parameters":[{"__symbolic":"reference","name":"RecursivePartial","module":"@ngx-grpc/common","arguments":[{"__symbolic":"select","expression":{"__symbolic":"reference","name":"CreateCustomPhonemizerRequest"},"member":"AsObject"}]}]}],"serializeBinary":[{"__symbolic":"method"}],"toObject":[{"__symbolic":"method"}],"toJSON":[{"__symbolic":"method"}],"toProtobufJSON":[{"__symbolic":"method"}]},"statics":{"id":"ondewo.t2s.CustomPhonemizerProto"}},"Map":{"__symbolic":"class","members":{"__ctor__":[{"__symbolic":"constructor","parameters":[{"__symbolic":"reference","name":"RecursivePartial","module":"@ngx-grpc/common","arguments":[{"__symbolic":"select","expression":{"__symbolic":"reference","name":"CreateCustomPhonemizerRequest"},"member":"AsObject"}]}]}],"serializeBinary":[{"__symbolic":"method"}],"toObject":[{"__symbolic":"method"}],"toJSON":[{"__symbolic":"method"}],"toProtobufJSON":[{"__symbolic":"method"}]},"statics":{"id":"ondewo.t2s.Map"}},"ListCustomPhonemizerResponse":{"__symbolic":"class","members":{"__ctor__":[{"__symbolic":"constructor","parameters":[{"__symbolic":"reference","name":"RecursivePartial","module":"@ngx-grpc/common","arguments":[{"__symbolic":"select","expression":{"__symbolic":"reference","name":"CreateCustomPhonemizerRequest"},"member":"AsObject"}]}]}],"serializeBinary":[{"__symbolic":"method"}],"toObject":[{"__symbolic":"method"}],"toJSON":[{"__symbolic":"method"}],"toProtobufJSON":[{"__symbolic":"method"}]},"statics":{"id":"ondewo.t2s.ListCustomPhonemizerResponse"}},"ListCustomPhonemizerRequest":{"__symbolic":"class","members":{"__ctor__":[{"__symbolic":"constructor","parameters":[{"__symbolic":"reference","name":"RecursivePartial","module":"@ngx-grpc/common","arguments":[{"__symbolic":"select","expression":{"__symbolic":"reference","name":"CreateCustomPhonemizerRequest"},"member":"AsObject"}]}]}],"serializeBinary":[{"__symbolic":"method"}],"toObject":[{"__symbolic":"method"}],"toJSON":[{"__symbolic":"method"}],"toProtobufJSON":[{"__symbolic":"method"}]},"statics":{"id":"ondewo.t2s.ListCustomPhonemizerRequest"}},"UpdateCustomPhonemizerRequest":{"__symbolic":"class","members":{"__ctor__":[{"__symbolic":"constructor","parameters":[{"__symbolic":"reference","name":"RecursivePartial","module":"@ngx-grpc/common","arguments":[{"__symbolic":"select","expression":{"__symbolic":"reference","name":"CreateCustomPhonemizerRequest"},"member":"AsObject"}]}]}],"serializeBinary":[{"__symbolic":"method"}],"toObject":[{"__symbolic":"method"}],"toJSON":[{"__symbolic":"method"}],"toProtobufJSON":[{"__symbolic":"method"}]},"statics":{"id":"ondewo.t2s.UpdateCustomPhonemizerRequest"}},"CreateCustomPhonemizerRequest":{"__symbolic":"class","members":{"__ctor__":[{"__symbolic":"constructor","parameters":[{"__symbolic":"reference","name":"RecursivePartial","module":"@ngx-grpc/common","arguments":[{"__symbolic":"select","expression":{"__symbolic":"reference","name":"CreateCustomPhonemizerRequest"},"member":"AsObject"}]}]}],"serializeBinary":[{"__symbolic":"method"}],"toObject":[{"__symbolic":"method"}],"toJSON":[{"__symbolic":"method"}],"toProtobufJSON":[{"__symbolic":"method"}]},"statics":{"id":"ondewo.t2s.CreateCustomPhonemizerRequest"}},"GRPC_TEXT2_SPEECH_CLIENT_SETTINGS":{"__symbolic":"new","expression":{"__symbolic":"reference","module":"@angular/core","name":"InjectionToken","line":11,"character":53},"arguments":["GRPC_TEXT2_SPEECH_CLIENT_SETTINGS"]},"GRPC_CUSTOM_PHONEMIZERS_CLIENT_SETTINGS":{"__symbolic":"new","expression":{"__symbolic":"reference","module":"@angular/core","name":"InjectionToken","line":11,"character":59},"arguments":["GRPC_CUSTOM_PHONEMIZERS_CLIENT_SETTINGS"]},"Text2SpeechClient":{"__symbolic":"class","decorators":[{"__symbolic":"call","expression":{"__symbolic":"reference","module":"@angular/core","name":"Injectable","line":26,"character":1},"arguments":[{"providedIn":"any"}]}],"members":{"__ctor__":[{"__symbolic":"constructor","parameterDecorators":[[{"__symbolic":"call","expression":{"__symbolic":"reference","module":"@angular/core","name":"Optional","line":228,"character":5}},{"__symbolic":"call","expression":{"__symbolic":"reference","module":"@angular/core","name":"Inject","line":228,"character":17},"arguments":[{"__symbolic":"reference","name":"GRPC_TEXT2_SPEECH_CLIENT_SETTINGS"}]}],[{"__symbolic":"call","expression":{"__symbolic":"reference","module":"@angular/core","name":"Inject","line":229,"character":5},"arguments":[{"__symbolic":"reference","module":"@ngx-grpc/core","name":"GRPC_CLIENT_FACTORY","line":229,"character":12}]}],null],"parameters":[{"__symbolic":"reference","name":"any"},{"__symbolic":"reference","name":"GrpcClientFactory","module":"@ngx-grpc/common","arguments":[{"__symbolic":"reference","name":"any"}]},{"__symbolic":"reference","module":"@ngx-grpc/core","name":"GrpcHandler","line":230,"character":21}]}],"synthesize":[{"__symbolic":"method"}],"batchSynthesize":[{"__symbolic":"method"}],"getT2sPipeline":[{"__symbolic":"method"}],"createT2sPipeline":[{"__symbolic":"method"}],"deleteT2sPipeline":[{"__symbolic":"method"}],"updateT2sPipeline":[{"__symbolic":"method"}],"listT2sPipelines":[{"__symbolic":"method"}],"listT2sLanguages":[{"__symbolic":"method"}],"listT2sDomains":[{"__symbolic":"method"}]},"statics":{"ɵprov":{}}},"CustomPhonemizersClient":{"__symbolic":"class","decorators":[{"__symbolic":"call","expression":{"__symbolic":"reference","module":"@angular/core","name":"Injectable","line":26,"character":1},"arguments":[{"providedIn":"any"}]}],"members":{"__ctor__":[{"__symbolic":"constructor","parameterDecorators":[[{"__symbolic":"call","expression":{"__symbolic":"reference","module":"@angular/core","name":"Optional","line":144,"character":5}},{"__symbolic":"call","expression":{"__symbolic":"reference","module":"@angular/core","name":"Inject","line":144,"character":17},"arguments":[{"__symbolic":"reference","name":"GRPC_CUSTOM_PHONEMIZERS_CLIENT_SETTINGS"}]}],[{"__symbolic":"call","expression":{"__symbolic":"reference","module":"@angular/core","name":"Inject","line":145,"character":5},"arguments":[{"__symbolic":"reference","module":"@ngx-grpc/core","name":"GRPC_CLIENT_FACTORY","line":145,"character":12}]}],null],"parameters":[{"__symbolic":"reference","name":"any"},{"__symbolic":"reference","name":"GrpcClientFactory","module":"@ngx-grpc/common","arguments":[{"__symbolic":"reference","name":"any"}]},{"__symbolic":"reference","module":"@ngx-grpc/core","name":"GrpcHandler","line":146,"character":21}]}],"getCustomPhonemizer":[{"__symbolic":"method"}],"createCustomPhonemizer":[{"__symbolic":"method"}],"deleteCustomPhonemizer":[{"__symbolic":"method"}],"updateCustomPhonemizer":[{"__symbolic":"method"}],"listCustomPhonemizer":[{"__symbolic":"method"}]},"statics":{"ɵprov":{}}}},"origins":{"Pcm":"./api/ondewo/t2s/text-to-speech.pb","AudioFormat":"./api/ondewo/t2s/text-to-speech.pb","SynthesizeRequest":"./api/ondewo/t2s/text-to-speech.pb","BatchSynthesizeRequest":"./api/ondewo/t2s/text-to-speech.pb","BatchSynthesizeResponse":"./api/ondewo/t2s/text-to-speech.pb","RequestConfig":"./api/ondewo/t2s/text-to-speech.pb","SynthesizeResponse":"./api/ondewo/t2s/text-to-speech.pb","GetServiceInfoResponse":"./api/ondewo/t2s/text-to-speech.pb","ListT2sPipelinesRequest":"./api/ondewo/t2s/text-to-speech.pb","ListT2sPipelinesResponse":"./api/ondewo/t2s/text-to-speech.pb","ListT2sLanguagesRequest":"./api/ondewo/t2s/text-to-speech.pb","ListT2sLanguagesResponse":"./api/ondewo/t2s/text-to-speech.pb","ListT2sDomainsRequest":"./api/ondewo/t2s/text-to-speech.pb","ListT2sDomainsResponse":"./api/ondewo/t2s/text-to-speech.pb","T2sPipelineId":"./api/ondewo/t2s/text-to-speech.pb","Text2SpeechConfig":"./api/ondewo/t2s/text-to-speech.pb","Description":"./api/ondewo/t2s/text-to-speech.pb","Inference":"./api/ondewo/t2s/text-to-speech.pb","CompositeInference":"./api/ondewo/t2s/text-to-speech.pb","Text2Mel":"./api/ondewo/t2s/text-to-speech.pb","GlowTTS":"./api/ondewo/t2s/text-to-speech.pb","GlowTTSTriton":"./api/ondewo/t2s/text-to-speech.pb","Mel2Audio":"./api/ondewo/t2s/text-to-speech.pb","HiFiGan":"./api/ondewo/t2s/text-to-speech.pb","HiFiGanTriton":"./api/ondewo/t2s/text-to-speech.pb","MbMelganTriton":"./api/ondewo/t2s/text-to-speech.pb","Caching":"./api/ondewo/t2s/text-to-speech.pb","Normalization":"./api/ondewo/t2s/text-to-speech.pb","Postprocessing":"./api/ondewo/t2s/text-to-speech.pb","Logmnse":"./api/ondewo/t2s/text-to-speech.pb","Wiener":"./api/ondewo/t2s/text-to-speech.pb","Apodization":"./api/ondewo/t2s/text-to-speech.pb","PhonemizerId":"./api/ondewo/t2s/custom-phonemizer.pb","CustomPhonemizerProto":"./api/ondewo/t2s/custom-phonemizer.pb","Map":"./api/ondewo/t2s/custom-phonemizer.pb","ListCustomPhonemizerResponse":"./api/ondewo/t2s/custom-phonemizer.pb","ListCustomPhonemizerRequest":"./api/ondewo/t2s/custom-phonemizer.pb","UpdateCustomPhonemizerRequest":"./api/ondewo/t2s/custom-phonemizer.pb","CreateCustomPhonemizerRequest":"./api/ondewo/t2s/custom-phonemizer.pb","GRPC_TEXT2_SPEECH_CLIENT_SETTINGS":"./api/ondewo/t2s/text-to-speech.pbconf","GRPC_CUSTOM_PHONEMIZERS_CLIENT_SETTINGS":"./api/ondewo/t2s/custom-phonemizer.pbconf","Text2SpeechClient":"./api/ondewo/t2s/text-to-speech.pbsc","CustomPhonemizersClient":"./api/ondewo/t2s/custom-phonemizer.pbsc"},"importAs":"@ondewo/t2s-client-angular"}